ShippingContainerNumberValidate/__init__.py
ShippingContainerNumberValidate-1.0.8.dist-info/METADATA
ShippingContainerNumberValidate-1.0.8.dist-info/WHEEL
ShippingContainerNumberValidate-1.0.8.dist-info/top_level.txt
ShippingContainerNumberValidate-1.0.8.dist-info/RECORD
