Metadata-Version: 2.1
Name: ShippingContainerNumberValidate
Version: 1.0.8
Summary: Helps you validate a shipping container number as per ISO 6346 standard
Home-page: https://github.com/anujpanchal57/ContainerNumberValidate
Author: Anuj Panchal
Author-email: anujpanchal57@gmail.com
License: MIT
Keywords: Shipping,Logistics,Container Number,Shipping Container,Exports,Imports,Validate Shipping Container Number
Classifier: Intended Audience :: Developers
Classifier: License :: OSI Approved :: MIT License
Classifier: Programming Language :: Python :: 3
Classifier: Programming Language :: Python :: 3.9
